django_nested_formset-0.1.2.dist-info/DESCRIPTION.rst
django_nested_formset-0.1.2.dist-info/METADATA
django_nested_formset-0.1.2.dist-info/metadata.json
django_nested_formset-0.1.2.dist-info/RECORD
django_nested_formset-0.1.2.dist-info/top_level.txt
django_nested_formset-0.1.2.dist-info/WHEEL
nested_formset/__init__.py
nested_formset/test_settings.py
nested_formset/tests/__init__.py
nested_formset/tests/models.py
nested_formset/tests/test_factory.py
nested_formset/tests/test_instantiation.py
nested_formset/tests/test_properties.py
nested_formset/tests/test_save.py
nested_formset/tests/test_validation.py
nested_formset/tests/util.py
