Metadata-Version: 2.0
Name: django-nested-formset
Version: 0.1.2
Summary: Nest Django formsets for multi-level hierarchical editing
Home-page: https://github.com/nyergler/nested-formset
Author: Nathan Yergler
Author-email: nathan@yergler.net
License: BSD
Platform: UNKNOWN
Classifier: License :: OSI Approved :: BSD License
Classifier: Development Status :: 4 - Beta
Classifier: Framework :: Django
Classifier: Operating System :: OS Independent
Classifier: Programming Language :: Python :: 2.7
Classifier: Programming Language :: Python :: 3.3
Classifier: Programming Language :: Python :: 3.4
Requires-Dist: Django (>=1.5)
